.DS_Store
echomorse-0.8.3.dist-info/METADATA
echomorse-0.8.3.dist-info/WHEEL
echomorse-0.8.3.dist-info/entry_points.txt
echomorse-0.8.3.dist-info/licenses/LICENSE
echomorse/.DS_Store
echomorse/__init__.py
echomorse/__main__.py
echomorse/audio/.DS_Store
echomorse/audio/dog_bark/.DS_Store
echomorse/audio/dog_bark/dog_bark_long.wav
echomorse/audio/dog_bark/dog_bark_short.wav
echomorse/audio/dog_bark/voice_config.json
echomorse/cli.py
echomorse/config.py
echomorse/interpreter/__init__.py
echomorse/interpreter/interpreter.py
echomorse/main.py
echomorse/synthesizer/__init__.py
echomorse/synthesizer/synthesizer.py
echomorse/translator/__init__.py
echomorse/translator/translator.py
echomorse/utils/__init__.py
echomorse/utils/create_dummy_audio.py
echomorse/utils/voice_manager.py
echomorse-0.8.3.dist-info/RECORD
