Metadata-Version: 2.1
Name: echomorse
Version: 0.8.3
Summary: A Python tool to translate text to Morse code audio using various voices.
Keywords: morse,morse code,audio,ham radio,cw,text-to-audio
Author-Email: Baksi Li <myself@baksili.codes>
License: MIT
Classifier: Development Status :: 4 - Beta
Classifier: Environment :: Console
Classifier: Intended Audience :: Developers
Classifier: Intended Audience :: Education
Classifier: Intended Audience :: Science/Research
Classifier: License :: OSI Approved :: MIT License
Classifier: Programming Language :: Python :: 3
Classifier: Programming Language :: Python :: 3.10
Classifier: Programming Language :: Python :: 3.11
Classifier: Programming Language :: Python :: 3.12
Classifier: Topic :: Communications :: Ham Radio
Classifier: Topic :: Multimedia :: Sound/Audio
Classifier: Topic :: Utilities
Project-URL: Homepage, https://github.com/BaksiLi/echomorse
Project-URL: Issues, https://github.com/BaksiLi/echomorse/issues
Project-URL: Documentation, https://github.com/BaksiLi/echomorse#readme
Requires-Python: <3.13,>=3.10
Requires-Dist: numpy>=2.2.5
Requires-Dist: pydub>=0.25.1
Requires-Dist: appdirs>=1.4.4
